{"is_source_file": true, "format": "JavaScript (React JSX)", "description": "This is the main app component for a React-based patient care management front-end, responsible for routing, layout, and authentication handling.", "external_files": ["./components/Sidebar", "./components/TopNavbar", "./pages/PatientList", "./pages/PatientDetail", "./pages/PatientForm", "./pages/Login", "./context/AuthContext", "./App.css"], "external_methods": ["useState", "useEffect", "useAuth"], "published": ["App"], "classes": [], "methods": [{"name": "DashboardLayout({ children })", "description": "Main layout component providing sidebar and top navbar wrapping child content.", "scope": "", "scopeKind": ""}, {"name": "App()", "description": "Root component managing routing and authentication protection.", "scope": "", "scopeKind": ""}], "calls": ["React.useState", "React.useEffect", "document.documentElement.setAttribute", "useAuth", "Navigate", "Router", "Routes", "Route"], "search-terms": ["React routing", "Dashboard layout", "Patient care management", "Protected routes", "AuthProvider", "useAuth hook"], "state": 2, "file_id": 7, "knowledge_revision": 25, "git_revision": "45daa9f6b6e68e6cb9bd5ba9662e8e6caa085998", "ctags": [{"_type": "tag", "name": "App", "path": "/home/kavia/workspace/code-generation/patient-care-management-system-10292-10301/patient_log_frontend/src/App.js", "pattern": "/^function App() {$/", "language": "JavaScript", "kind": "function", "signature": "()"}, {"_type": "tag", "name": "DashboardLayout", "path": "/home/kavia/workspace/code-generation/patient-care-management-system-10292-10301/patient_log_frontend/src/App.js", "pattern": "/^function DashboardLayout({ children }) {$/", "language": "JavaScript", "kind": "function", "signature": "({ children })"}, {"_type": "tag", "name": "children", "path": "/home/kavia/workspace/code-generation/patient-care-management-system-10292-10301/patient_log_frontend/src/App.js", "pattern": "/^  const ProtectedRoute = ({ children }) => {$/", "language": "JavaScript", "kind": "field", "scope": "App.ProtectedRoute", "scopeKind": "class"}], "hash": "ca21696678712e54a3397ac0ab1e742a", "format-version": 4, "code-base-name": "patient_log_frontend", "filename": "patient_log_frontend/src/App.js", "fields": [{"name": "const ProtectedRoute = ({ children }) => {", "scope": "App.ProtectedRoute", "scopeKind": "class", "description": "unavailable"}], "revision_history": [{"25": "45daa9f6b6e68e6cb9bd5ba9662e8e6caa085998"}]}